{
    "task_name": "arrange home modifications for elderly",
    "task_description": "Task to arrange home modifications for elderly",
    "budget": {
        "range": {
            "min": 1250,
            "max": 24000
        },
        "flexibility": "Unknown/Not sure",
        "payment_methods": [
            "Credit Card",
            "Cash",
            "Financing",
            "Insurance"
        ]
    },
    "preferences": {
        "must_have": [
            "Unknown/Not sure",
            "I'm not really sure what's important",
            "Not too expensive but decent"
        ],
        "nice_to_have": [
            "Upgrade lighting to motion-sensor fixtures",
            "Enhance kitchen accessibility with pull-out shelves",
            "Install a stairlift for multi-level homes",
            "Add soundproofing to reduce noise disturbances"
        ],
        "deal_breakers": [
            "Lack of available space for mobility aids like walkers or wheelchairs",
            "Failure to comply with local building codes and regulations"
        ]
    },
    "constraints": {
        "time": "Time constraint level 4",
        "location": "Any location",
        "technical": [],
        "other": []
    },
    "knowledge_level": "Intermediate",
    "urgency": "Moderate",
    "decision_factors": [
        "Type of home modifications needed",
        "Budget constraints",
        "Safety requirements",
        "Aging in place preferences",
        "Timeframe for completion",
        "Availability of contractors"
    ],
    "task_requirements": {
        "technical": [
            "I think I need something that can handle a lot of weight but I'm not sure how to measure that",
            "Maybe something modern that works with the existing walls, or maybe not?",
            "I heard smart technology is important but not sure what it means here"
        ],
        "non_technical": [
            "Good performance in terms of looks but also needs to be easy to use, I guess",
            "I want it to feel cozy but also spacious, even though I know those might not go together",
            "Unknown/Not sure about what colors would work best for an elderly person"
        ]
    },
    "success_criteria": {
        "must_meet": [
            "Must not be too difficult to understand or operate, whatever that means",
            "Needs to be affordable but also look expensive, which seems contradictory"
        ],
        "should_meet": [
            "Should comply with some kind of safety standards, but I don’t know which ones",
            "Should help with mobility but also look nice, if that's possible"
        ],
        "nice_to_meet": [
            "Nice if it has features for tech-savvy seniors, whatever that means",
            "Nice to have something that could blend in with the current decor, though I'm not sure how"
        ]
    },
    "metadata": {
        "generation_timestamp": "2025-05-13T21:35:46.103734",
        "task": "arrange home modifications for elderly",
        "difficulty_level": 4,
        "option_number": 4,
        "total_options": 5,
        "model_type": "GPT_4O_MINI",
        "uncertainty_score": 8,
        "is_uncertain": true
    }
}