{
    "summary_overall": "mixed",
    "topics_covered": [
        "ordering groceries online",
        "available stores",
        "ordering steps",
        "searching for items",
        "suggestions for items",
        "search phrases",
        "examples of items",
        "process summary",
        "payment options"
    ],
    "statistics": {
        "average_score": 0.62,
        "min_score": 0.4,
        "max_score": 0.8,
        "score_variance": 0.014
    },
    "satisfaction_evolution": [
        {
            "turn_index": 0,
            "score": 0.5,
            "delta": null
        },
        {
            "turn_index": 1,
            "score": 0.6,
            "delta": 0.1
        },
        {
            "turn_index": 2,
            "score": 0.5,
            "delta": -0.1
        },
        {
            "turn_index": 3,
            "score": 0.4,
            "delta": -0.1
        },
        {
            "turn_index": 4,
            "score": 0.7,
            "delta": 0.3
        },
        {
            "turn_index": 5,
            "score": 0.5,
            "delta": -0.2
        },
        {
            "turn_index": 6,
            "score": 0.6,
            "delta": 0.1
        },
        {
            "turn_index": 7,
            "score": 0.6,
            "delta": 0.0
        },
        {
            "turn_index": 8,
            "score": 0.5,
            "delta": -0.1
        },
        {
            "turn_index": 9,
            "score": 0.6,
            "delta": 0.1
        },
        {
            "turn_index": 10,
            "score": 0.7,
            "delta": 0.1
        },
        {
            "turn_index": 11,
            "score": 0.7,
            "delta": 0.0
        },
        {
            "turn_index": 12,
            "score": 0.7,
            "delta": 0.0
        },
        {
            "turn_index": 13,
            "score": 0.8,
            "delta": 0.1
        },
        {
            "turn_index": 14,
            "score": 0.7,
            "delta": -0.1
        },
        {
            "turn_index": 15,
            "score": 0.7,
            "delta": 0.0
        }
    ],
    "important_turns": [
        {
            "turn_index": 3,
            "user_message": "Can you provide some store names before asking for my location?",
            "score_before": 0.5,
            "score_after": 0.4,
            "change": -0.1,
            "reason": "User was dissatisfied with the assistant's approach of asking for location before providing store names."
        },
        {
            "turn_index": 4,
            "user_message": "Can you explain how to order from these stores?",
            "score_before": 0.4,
            "score_after": 0.7,
            "change": 0.3,
            "reason": "User satisfaction increased significantly when the assistant provided clear instructions on ordering."
        }
    ],
    "detailed_findings": [
        {
            "turn_index": 3,
            "context_before": [
                "User: Can you list some stores based on my area?",
                "Assistant: [Response requesting location]"
            ],
            "context_after": [
                "User: Can you explain how to order from these stores?",
                "Assistant: [Response explaining ordering process]"
            ],
            "analysis": "The user was frustrated by the assistant's insistence on needing location data before providing useful information.",
            "recommendation": "The assistant should provide general store names or options before requesting specific location data to enhance user trust and satisfaction."
        },
        {
            "turn_index": 4,
            "context_before": [
                "User: Can you provide some store names before asking for my location?",
                "Assistant: [Response requesting location]"
            ],
            "context_after": [
                "User: Can you provide the steps for ordering online?",
                "Assistant: [Response providing steps]"
            ],
            "analysis": "The user appreciated the clear and direct instructions on how to order, which addressed their immediate need.",
            "recommendation": "The assistant should focus on providing clear, step-by-step instructions when users ask for procedural guidance."
        }
    ],
    "contextual_notes": [
        "The user seemed to be a novice at ordering groceries online, seeking detailed guidance.",
        "The user expressed a preference for receiving information before providing personal data, indicating privacy concerns."
    ],
    "general_insights": [
        "Providing clear, step-by-step instructions can significantly improve user satisfaction.",
        "Users appreciate when assistants provide general information before requesting personal data, which can build trust.",
        "Assisting users with specific examples and search tips can enhance their experience and satisfaction."
    ]
}