{
    "summary_overall": "positive",
    "topics_covered": [
        "appointment setup",
        "accessibility",
        "communication",
        "response times",
        "reminders",
        "customization of reminders",
        "presentation of options",
        "support during scheduling",
        "finding providers",
        "reading reviews"
    ],
    "statistics": {
        "average_score": 0.86,
        "min_score": 0.5,
        "max_score": 1.0,
        "score_variance": 0.0331
    },
    "satisfaction_evolution": [
        {
            "turn_index": 0,
            "score": 0.5,
            "delta": null
        },
        {
            "turn_index": 1,
            "score": 0.5,
            "delta": 0.0
        },
        {
            "turn_index": 2,
            "score": 0.6,
            "delta": 0.1
        },
        {
            "turn_index": 3,
            "score": 0.7,
            "delta": 0.1
        },
        {
            "turn_index": 4,
            "score": 0.8,
            "delta": 0.1
        },
        {
            "turn_index": 5,
            "score": 0.9,
            "delta": 0.1
        },
        {
            "turn_index": 6,
            "score": 0.8,
            "delta": -0.1
        },
        {
            "turn_index": 7,
            "score": 0.9,
            "delta": 0.1
        },
        {
            "turn_index": 8,
            "score": 0.9,
            "delta": 0.0
        },
        {
            "turn_index": 9,
            "score": 1.0,
            "delta": 0.1
        },
        {
            "turn_index": 10,
            "score": 1.0,
            "delta": 0.0
        },
        {
            "turn_index": 11,
            "score": 1.0,
            "delta": 0.0
        },
        {
            "turn_index": 12,
            "score": 1.0,
            "delta": 0.0
        },
        {
            "turn_index": 13,
            "score": 1.0,
            "delta": 0.0
        },
        {
            "turn_index": 14,
            "score": 0.9,
            "delta": -0.1
        },
        {
            "turn_index": 15,
            "score": 1.0,
            "delta": 0.1
        }
    ],
    "important_turns": [
        {
            "turn_index": 0,
            "user_message": "I'm looking to set up an appointment, but I'm not sure where to start.",
            "score_before": null,
            "score_after": 0.5,
            "change": null,
            "reason": "Initial uncertainty and lack of direction."
        },
        {
            "turn_index": 5,
            "user_message": "Could we delve into how they communicate about these services?",
            "score_before": 0.8,
            "score_after": 0.9,
            "change": 0.1,
            "reason": "Increased satisfaction due to detailed communication information."
        },
        {
            "turn_index": 9,
            "user_message": "Could we clarify how these options are presented during the setting up process?",
            "score_before": 0.9,
            "score_after": 1.0,
            "change": 0.1,
            "reason": "Clarity on presentation of options led to full satisfaction."
        }
    ],
    "detailed_findings": [
        {
            "turn_index": 0,
            "context_before": [],
            "context_after": [
                "User: Maybe we can go through options without diving deep?"
            ],
            "analysis": "The user expressed uncertainty about how to begin the process, indicating a need for clear guidance.",
            "recommendation": "Provide a clear, step-by-step guide to setting up an appointment to improve initial satisfaction."
        },
        {
            "turn_index": 5,
            "context_before": [
                "User: Could we maybe discuss how they help with appointments?"
            ],
            "context_after": [
                "User: How about we touch on the response times for assistance?"
            ],
            "analysis": "The user showed increased satisfaction when communication methods were clarified, indicating the importance of transparency.",
            "recommendation": "Ensure communication methods are clearly explained and accessible to users."
        },
        {
            "turn_index": 9,
            "context_before": [
                "User: Is there a way to customize those reminder settings?"
            ],
            "context_after": [
                "User: Could we talk about any available support during that online scheduling?"
            ],
            "analysis": "The user reached full satisfaction when the presentation of options was clarified, highlighting the importance of user-friendly interfaces.",
            "recommendation": "Focus on enhancing the user interface to make options easily understandable and accessible."
        }
    ],
    "contextual_notes": [
        "The user started with low satisfaction due to uncertainty but showed a positive trend as clarity and information were provided.",
        "The conversation focused on practical aspects of scheduling and communication, indicating a user preference for actionable information."
    ],
    "general_insights": [
        "Providing clear, step-by-step guidance can significantly enhance user satisfaction, especially for users unfamiliar with the process.",
        "Transparency in communication methods and options presentation is crucial for maintaining high satisfaction levels.",
        "User-friendly interfaces and customization options can lead to increased user satisfaction and engagement."
    ]
}