{
    "summary_overall": "positive",
    "topics_covered": [
        "finding suitable phone options",
        "listing requirements",
        "exploring available choices",
        "confidence in decision-making",
        "seeking additional information",
        "importance of support and guidance"
    ],
    "statistics": {
        "average_score": 0.835,
        "min_score": 0.5,
        "max_score": 0.9,
        "score_variance": 0.021
    },
    "satisfaction_evolution": [
        {
            "turn_index": 0,
            "score": 0.5,
            "delta": null
        },
        {
            "turn_index": 1,
            "score": 0.6,
            "delta": 0.1
        },
        {
            "turn_index": 2,
            "score": 0.8,
            "delta": 0.2
        },
        {
            "turn_index": 3,
            "score": 0.9,
            "delta": 0.1
        },
        {
            "turn_index": 4,
            "score": 0.8,
            "delta": -0.1
        },
        {
            "turn_index": 5,
            "score": 0.9,
            "delta": 0.1
        },
        {
            "turn_index": 6,
            "score": 0.9,
            "delta": 0.0
        },
        {
            "turn_index": 7,
            "score": 0.8,
            "delta": -0.1
        },
        {
            "turn_index": 8,
            "score": 0.9,
            "delta": 0.1
        },
        {
            "turn_index": 9,
            "score": 0.7,
            "delta": -0.2
        },
        {
            "turn_index": 10,
            "score": 0.85,
            "delta": 0.15
        },
        {
            "turn_index": 11,
            "score": 0.8,
            "delta": -0.05
        },
        {
            "turn_index": 12,
            "score": 0.9,
            "delta": 0.1
        },
        {
            "turn_index": 13,
            "score": 0.85,
            "delta": -0.05
        },
        {
            "turn_index": 14,
            "score": 0.9,
            "delta": 0.05
        },
        {
            "turn_index": 15,
            "score": 0.9,
            "delta": 0.0
        }
    ],
    "important_turns": [
        {
            "turn_index": 2,
            "user_message": "We need to find some options that really fit those requirements.",
            "score_before": 0.6,
            "score_after": 0.8,
            "change": 0.2,
            "reason": "The user appreciated the assistant's effort in identifying options that meet specific requirements."
        },
        {
            "turn_index": 9,
            "user_message": "Just a bit more information might be what I need to finalize things!",
            "score_before": 0.9,
            "score_after": 0.7,
            "change": -0.2,
            "reason": "The user expressed a need for more information, indicating a gap in the provided details."
        }
    ],
    "detailed_findings": [
        {
            "turn_index": 2,
            "context_before": [
                "User: Finding something that fits her could be a bit tricky.",
                "Assistant: [Response not provided]"
            ],
            "context_after": [
                "User: Listing those would be really useful!",
                "Assistant: [Response not provided]"
            ],
            "analysis": "The user felt more satisfied as the conversation progressed towards identifying specific options, indicating that the assistant's responses were aligned with the user's needs.",
            "recommendation": "The assistant should continue to focus on providing tailored options that align closely with user requirements to maintain and increase satisfaction."
        },
        {
            "turn_index": 9,
            "context_before": [
                "User: That should really help in making a confident decision!",
                "Assistant: [Response not provided]"
            ],
            "context_after": [
                "User: This could definitely help ease my mind about making a purchase!",
                "Assistant: [Response not provided]"
            ],
            "analysis": "The user's satisfaction decreased due to a lack of sufficient information, highlighting the need for more comprehensive responses.",
            "recommendation": "The assistant should ensure that all necessary information is provided to the user, potentially offering additional resources or clarifications proactively."
        }
    ],
    "contextual_notes": [
        "The user is seeking assistance in choosing a phone for their mother, indicating a personal and potentially emotional investment in the decision.",
        "The conversation reflects a balance between seeking detailed information and the emotional reassurance of support."
    ],
    "general_insights": [
        "Providing detailed, tailored options can significantly enhance user satisfaction.",
        "Proactively offering additional information and resources can prevent dips in user satisfaction.",
        "Emotional support and reassurance are crucial in conversations involving personal decisions."
    ]
}