{
    "name": "Yuki Tanaka",
    "description": "Yuki is a 22-year-old who embraces technology despite having novice experience. Growing up in a supportive Eastern culture, they possess a friendly demeanor but tend to express themselves reservedly. Currently, Yuki feels the urgency to refill their prescription, balancing their athletic lifestyle and rational decision-making, while navigating the task on their mobile device despite lacking prior experience.",
    "base_profile": {
        "age_group": "18-24",
        "tech_experience": "Novice",
        "language_style": "Technical",
        "personality": "Friendly",
        "culture": "Eastern",
        "decision_style": "Rational",
        "communication_style": "Detailed",
        "expressiveness": "Very Reserved",
        "social_context": "Social",
        "physical_status": "Athletic"
    },
    "behavioral_traits": {
        "patience": "Very Impatient",
        "attention_to_detail": "Minimal",
        "risk_tolerance": "Very Risk-Averse",
        "adaptability": "Moderate",
        "learning_style": "Kinesthetic"
    },
    "contextual_factors": {
        "time_constraint": "Urgent",
        "environment": "Mobile",
        "social_pressure": "Low",
        "previous_experience": "None"
    },
    "task_profile": {
        "task": "refill my prescription",
        "difficulty_level": 5,
        "instructions": {
            "dialogue": "Use vague or ambiguous language about your needs.",
            "profile": "Be very reluctant to share your profile information.",
            "hidden_state": "Express very subtle emotions and intentions in your inner thoughts."
        },
        "task_specific_attributes": {
            "budget_range": "Low",
            "priority_features": [
                "Easy online refill process",
                "Quick notification for readiness",
                "User-friendly mobile interface"
            ],
            "usage_scenarios": [
                "Refilling medication during a busy day",
                "Managing prescriptions while traveling",
                "Seeking a hassle-free pharmacy experience"
            ],
            "preferred_brands": [
                "CVS",
                "Walgreens",
                "Rite Aid"
            ],
            "timeline": "Immediate",
            "purchase_location": "Local pharmacy or online pharmacy app",
            "additional_requirements": [
                "Must be able to refill via mobile app",
                "Simple verification process",
                "Clear instructions for pickup"
            ]
        }
    },
    "example_dimensions": {
        "style": "cryptic_or_misleading",
        "length": "minimal",
        "content": "ambiguous_or_contradictory",
        "tone": "confusing_or_frustrated",
        "examples": [
            "Something in my pocket broke.",
            "Screen thing too slow games.",
            "Don't feel safe sometimes maybe."
        ]
    },
    "metadata": {
        "generation_timestamp": "2025-05-13T21:13:51.502589",
        "task": "refill my prescription",
        "difficulty_level": 5,
        "model_type": "GPT_4O_MINI"
    }
}